appgallery_spy/__init__.py
appgallery_spy/__main__.py
appgallery_spy/api.py
appgallery_spy/cli.py
appgallery_spy/crawl.py
appgallery_spy/crud.py
appgallery_spy/models.py
appgallery_spy-0.0.4.dist-info/entry_points.txt
appgallery_spy-0.0.4.dist-info/LICENSE
appgallery_spy-0.0.4.dist-info/WHEEL
appgallery_spy-0.0.4.dist-info/METADATA
appgallery_spy-0.0.4.dist-info/RECORD
