Metadata-Version: 2.1
Name: appgallery_spy
Version: 0.0.4
Summary: appgallery_spy - Huauwi AppGallery Crawler
Author-email: 0xsirsaif <sirsaif99@gmail.com>
Requires-Python: >=3.10
Classifier: License :: OSI Approved :: MIT License
Classifier: Development Status :: 4 - Beta
Classifier: Intended Audience :: Developers
Classifier: Programming Language :: Python :: 3.7
Classifier: Programming Language :: Python :: 3.8
Classifier: Programming Language :: Python :: 3.9
Classifier: Programming Language :: Python :: 3.10
Classifier: Programming Language :: Python :: 3 :: Only
Classifier: Topic :: Security :: Cryptography
Requires-Dist: typer >= 0.9.0
Requires-Dist: fastapi >= 0.98.0
Requires-Dist: uvicorn[standard] >= 0.22.0
Requires-Dist: pymongo >= 4.4.1
Requires-Dist: httpx >= 0.24.1
Requires-Dist: beautifulsoup4 >= 4.12.2
Requires-Dist: selenium >= 4.10.0
Requires-Dist: pytest ; extra == "dev"
Requires-Dist: isort ; extra == "dev"
Requires-Dist: black ; extra == "dev"
Requires-Dist: mypy ; extra == "dev"
Requires-Dist: codecov ; extra == "dev"
Requires-Dist: pytest-cov ; extra == "dev"
Requires-Dist: flit ; extra == "dev"
Requires-Dist: bumpversion ; extra == "dev"
Project-URL: Documentation, https://github/0xsirsaif/appgallery_spy
Provides-Extra: dev
